calltraces/ReadMe.md
calltraces/__init__.py
calltraces/classtrace.py
"calltraces/classtrace.py,cover"
calltraces/functiontrace.py
"calltraces/functiontrace.py,cover"
calltraces/linetrace.py
"calltraces/linetrace.py,cover"
calltraces/traceSettings.py
"calltraces/traceSettings.py,cover"
calltraces-2022.7.5.2.dist-info/LICENSE
calltraces-2022.7.5.2.dist-info/METADATA
calltraces-2022.7.5.2.dist-info/WHEEL
calltraces-2022.7.5.2.dist-info/top_level.txt
calltraces-2022.7.5.2.dist-info/RECORD
