Metadata-Version: 2.1
Name: calltraces
Version: 2022.7.5.2
Summary: A small package for tracing function calls
Author-email: "Righteous AI Inc." <admin@righteous.ai>
License: MIT License        
Keywords: calltraces,call,traces,stack,frames
Classifier: Intended Audience :: Developers
Classifier: License :: OSI Approved :: MIT License
Classifier: Operating System :: OS Independent
Classifier: Programming Language :: Python :: 3
Classifier: Programming Language :: Python :: 3.8
Classifier: Programming Language :: Python :: 3.9
Classifier: Programming Language :: Python :: 3.10
Classifier: Programming Language :: Python :: 3 :: Only
Requires-Python: >=3.8
License-File: LICENSE
Requires-Dist: colorama (>=0.4.4)
